Metadata-Version: 2.1
Name: basicqiwip2p
Version: 0.0.3
Summary: Basic set of tools for working with QiwiP2P
Home-page: https://github.com/MaYn3r/BasicQiwiP2P
Author-email: mayneryt@bk.ru
